whatsmyip/__init__.py
whatsmyip/__version__.py
whatsmyip/ip.py
whatsmyip/providers.py
whatsmyip/cli/__init__.py
whatsmyip/cli/main.py
whatsmyip-0.1.4.dist-info/LICENSE.md
whatsmyip-0.1.4.dist-info/METADATA
whatsmyip-0.1.4.dist-info/WHEEL
whatsmyip-0.1.4.dist-info/entry_points.txt
whatsmyip-0.1.4.dist-info/top_level.txt
whatsmyip-0.1.4.dist-info/RECORD
