Metadata-Version: 2.1
Name: whatsmyip
Version: 0.1.4
Summary: A tool to find your public IP address.
Home-page: https://github.com/Ecno92/whatsmyip
Author: Therry van Neerven
Author-email: mail@therryvanneerven.nl
License: MIT
Platform: win32
Platform: linux
Classifier: License :: OSI Approved :: MIT License
Classifier: Programming Language :: Python :: 3
Classifier: Programming Language :: Python :: 3.6
Classifier: Programming Language :: Python :: 3.7
Classifier: Programming Language :: Python :: Implementation :: CPython
Classifier: Topic :: Utilities
Classifier: Environment :: Console
Requires-Python: >=3.6.0
Requires-Dist: dnspython (>=1.15.0)
Requires-Dist: requests (>=2.12.4)
Requires-Dist: urllib3 (>=1.24.2)
Requires-Dist: click (>=6.7)
